wsat/__init__.py
wsat/wsat_extraplots.py
wsat/wsat_loadwind.py
wsat/wsat_windplot.py
wsat-0.1.3.dist-info/METADATA
wsat-0.1.3.dist-info/WHEEL
wsat-0.1.3.dist-info/RECORD
