Metadata-Version: 2.3
Name: wsat
Version: 0.1.3
Summary: A data visualization package
Author-email: "S.F.K" <Simonfogh@hotmail.com>
